hydra_plugins/hydra_colorlog/__init__.py
hydra_plugins/hydra_colorlog/colorlog.py
hydra_plugins/hydra_colorlog/conf/__init__.py
hydra_plugins/hydra_colorlog/conf/hydra/hydra_logging/colorlog.yaml
hydra_plugins/hydra_colorlog/conf/hydra/job_logging/colorlog.yaml
hydra_colorlog-1.2.0.dist-info/METADATA
hydra_colorlog-1.2.0.dist-info/WHEEL
hydra_colorlog-1.2.0.dist-info/top_level.txt
hydra_colorlog-1.2.0.dist-info/RECORD
