Metadata-Version: 2.1
Name: hydra-colorlog
Version: 1.2.0
Summary: Enables colorlog for Hydra apps
Home-page: https://github.com/facebookresearch/hydra/
Author: Omry Yadan
Author-email: omry@fb.com
License: UNKNOWN
Platform: UNKNOWN
Classifier: License :: OSI Approved :: MIT License
Classifier: Programming Language :: Python :: 3.6
Classifier: Programming Language :: Python :: 3.7
Classifier: Programming Language :: Python :: 3.8
Classifier: Programming Language :: Python :: 3.9
Classifier: Programming Language :: Python :: 3.10
Classifier: Operating System :: OS Independent
